LICENSE
README.md
setup.cfg
setup.py
d3g/__init__.py
d3g/angle.py
d3g/distance.py
d3g/vector.py
d3g.egg-info/PKG-INFO
d3g.egg-info/SOURCES.txt
d3g.egg-info/dependency_links.txt
d3g.egg-info/top_level.txt
images/line_eq1.png
images/line_eq2.png