Metadata-Version: 2.1
Name: d3g
Version: 0.4
Summary: Explore 3D geometry in python over here!
Home-page: https://github.com/vaish1999/3D-Geometry-in-Python
Author: Vaishakh Nargund
Author-email: vaishakh.nargund1999@gmail.com
License: GPL 2.0
Download-URL: https://github.com/vaish1999/3D-Geometry-in-Python/archive/v2.3.tar.gz
Keywords: 3d,geometry,line,plane,distance,python,vision
Platform: UNKNOWN
Classifier: Development Status :: 3 - Alpha
Classifier: Intended Audience :: Developers
Classifier: Topic :: Software Development :: Build Tools
Classifier: License :: OSI Approved :: GNU General Public License v2 (GPLv2)
Classifier: Programming Language :: Python :: 3
Classifier: Programming Language :: Python :: 3.4
Classifier: Programming Language :: Python :: 3.5
Classifier: Programming Language :: Python :: 3.6
Classifier: Programming Language :: Python :: 3.7
